firestore/__init__.py
firestore/exceptions.py
firestore/validators.py
firestore/async/__init__.py
firestore/containers/__init__.py
firestore/containers/collection.py
firestore/containers/document.py
firestore/datatypes/__init__.py
firestore/datatypes/_special_array.py
firestore/datatypes/array.py
firestore/datatypes/base.py
firestore/datatypes/boolean.py
firestore/datatypes/byte.py
firestore/datatypes/constants.py
firestore/datatypes/datatype.py
firestore/datatypes/float.py
firestore/datatypes/geopoint.py
firestore/datatypes/integer.py
firestore/datatypes/map.py
firestore/datatypes/null.py
firestore/datatypes/number.py
firestore/datatypes/reference.py
firestore/datatypes/string.py
firestore/datatypes/timestamp.py
firestore/db/__init__.py
firestore/db/cache.py
firestore/db/connection.py
firestore/db/connector.py
firestore/db/syncdb.py
firestore/errors/__init__.py
firestore/utils/__init__.py
firestore/utils/array.py
tests/__init__.py
tests/test_firestore_imports.py
tests/containers/__init__.py
tests/containers/collection_test.py
tests/containers/schema_test.py
tests/datatypes/__init__.py
tests/datatypes/array_test.py
tests/datatypes/base_test.py
tests/datatypes/boolean_test.py
tests/datatypes/collection_test.py
tests/datatypes/datatype_test.py
tests/datatypes/geopoint_test.py
tests/datatypes/map_test.py
tests/datatypes/number_test.py
tests/datatypes/reference_test.py
tests/datatypes/special_array_test.py
tests/datatypes/string_test.py
tests/datatypes/timestamp_test.py
tests/db/__init__.py
tests/db/connection_test.py
tests/db/connector_test.py
tests/db/resultset_test.py
firestore-0.0.8.dist-info/LICENSE
firestore-0.0.8.dist-info/METADATA
firestore-0.0.8.dist-info/WHEEL
firestore-0.0.8.dist-info/top_level.txt
firestore-0.0.8.dist-info/RECORD
