Metadata-Version: 1.1
Name: firestore
Version: 0.0.8
Summary: An offline-available ORM-like wrapper for Google Firestore Database
Home-page: https://github.com/workenvoy/firestore
Author: Workhamper
Author-email: raymond@workhamper.com
License: MIT
Platform: UNKNOWN
Classifier: Programming Language :: Python
Classifier: Programming Language :: Python :: 3.6
Classifier: Programming Language :: Python :: 3.7
Classifier: License :: OSI Approved :: MIT License
Classifier: Topic :: Database
